{"experiments":[{"baseLevel-popSize":30,"baseLevel-problemId":"SCHWEFEL223","baseLevel-sampleSize":30,"baseLevel-xDim":5,"baseLevelEvals":100,"bestParameters":{"OptimizerChainInitializerSimplex":{"perturbator":{"lowerBound":0.0,"upperBound":1.0,"value":0.013332670339153196},"refiner":{"lowerBound":0.0,"upperBound":1.0,"value":0.9866673296608468}},"OptimizerChainPerturbatorSimplex":{"refiner":{"lowerBound":0.0,"upperBound":1.0,"value":0.03484854336477602},"selector":{"lowerBound":0.0,"upperBound":1.0,"value":0.965151456635224}},"OptimizerChainRefinerSimplex":{"refiner":{"lowerBound":0.0,"upperBound":1.0,"value":0.07085544874282282},"selector":{"lowerBound":0.0,"upperBound":1.0,"value":0.9291445512571772}},"OptimizerChainSelectorSimplex":{"perturbator":{"lowerBound":0.0,"upperBound":1.0,"value":1.0}},"PerturbatorDEOperatorParams":{"DE_CR":{"lowerBound":0.9,"upperBound":1.0,"value":0.9925921423751369},"DE_FORCE":{"lowerBound":0.4,"upperBound":0.7,"value":0.5558050639207575}},"PerturbatorDESimplex":{"DE":{"lowerBound":0.0,"upperBound":1.0,"value":0.9610838603078151},"GA":{"lowerBound":0.0,"upperBound":1.0,"value":0.038916139692184916}},"PerturbatorGAOperatorParams":{"GA_ALPHA":{"lowerBound":0.0,"upperBound":1.0,"value":0.21828755460254887},"GA_CR":{"lowerBound":0.0,"upperBound":1.0,"value":0.5176231955548276},"GA_CR_POINT":{"lowerBound":0.0,"upperBound":1.0,"value":0.9431967218560205},"GA_MUTATION_RATE":{"lowerBound":0.0,"upperBound":1.0,"value":0.08308744652778076},"GA_MUTATION_SIZE":{"lowerBound":0.0,"upperBound":1000.0,"value":758.3402448080736},"GA_PARENTPOOL_RATIO":{"lowerBound":0.2,"upperBound":1.0,"value":0.9573158861389672}},"PerturbatorGASimplex":{"DE":{"lowerBound":0.0,"upperBound":1.0,"value":0.8225877397836493},"GA":{"lowerBound":0.0,"upperBound":1.0,"value":0.1774122602163507}},"PerturbatorInitializerSimplex":{"DE":{"lowerBound":0.0,"upperBound":1.0,"value":0.2865049518030164},"GA":{"lowerBound":0.0,"upperBound":1.0,"value":0.7134950481969836}},"RefinerGDOperatorParams":{"GD_ALPHA":{"lowerBound":0.5,"upperBound":5.0,"value":3.3396966927420157},"GD_FEVALS":{"lowerBound":1.0,"upperBound":100.0,"value":27.395358289075844}},"RefinerGDSimplex":{"GD":{"lowerBound":0.0,"upperBound":1.0,"value":0.3541278217735472},"LBFGS":{"lowerBound":0.0,"upperBound":1.0,"value":0.6458721782264528}},"RefinerInitializerSimplex":{"GD":{"lowerBound":0.0,"upperBound":1.0,"value":0.051180454826641464},"LBFGS":{"lowerBound":0.0,"upperBound":1.0,"value":0.9488195451733585}},"RefinerLBFGSOperatorParams":{"LBFGS_ALPHA":{"lowerBound":0.5,"upperBound":5.0,"value":3.517767600886917},"LBFGS_C1":{"lowerBound":0.0,"upperBound":0.1,"value":0.00956632069802239},"LBFGS_C2":{"lowerBound":0.8,"upperBound":1.0,"value":0.8979104152938038},"LBFGS_FEVALS":{"lowerBound":1.0,"upperBound":100.0,"value":12.430560311704726}},"RefinerLBFGSSimplex":{"GD":{"lowerBound":0.0,"upperBound":1.0,"value":0.5538727257207448},"LBFGS":{"lowerBound":0.0,"upperBound":1.0,"value":0.44612727427925525}},"SelectorBestSimplex":{"best":{"lowerBound":0.0,"upperBound":1.0,"value":1.0}},"SelectorInitializerSimplex":{"best":{"lowerBound":0.0,"upperBound":1.0,"value":1.0}}},"experimentHashSha256":"8fe1de66022d5ab767b8c33bf17671511313783240ce03475c3c7dcbfd844c1a","hyperLevel-id":"random","minBaseLevelStatistic":0.00011558894268340377,"trialCount":100,"trials":[{"atEval":3000,"med_+_iqr":1400930.167530895},{"atEval":6000,"med_+_iqr":0.0005543226842408017},{"atEval":9000,"med_+_iqr":353735117.9016991},{"atEval":12000,"med_+_iqr":7693785757.890813},{"atEval":15000,"med_+_iqr":75259130907.19044},{"atEval":18000,"med_+_iqr":1094939130064.7006},{"atEval":21000,"med_+_iqr":299222168624.9945},{"atEval":24000,"med_+_iqr":349225848510.2973},{"atEval":27000,"med_+_iqr":1093919163.8985443},{"atEval":30000,"med_+_iqr":354131241.54915535},{"atEval":33000,"med_+_iqr":72771591888.814},{"atEval":36000,"med_+_iqr":2105702383946.2295},{"atEval":39000,"med_+_iqr":17879061745.790215},{"atEval":42000,"med_+_iqr":41521008504.21479},{"atEval":45000,"med_+_iqr":189273463030.0384},{"atEval":48000,"med_+_iqr":1697936163.0623596},{"atEval":51000,"med_+_iqr":13738660.82993461},{"atEval":54000,"med_+_iqr":321926855655.1632},{"atEval":57000,"med_+_iqr":328853901.2552534},{"atEval":60000,"med_+_iqr":869222580.8331097},{"atEval":63000,"med_+_iqr":48812499928.25951},{"atEval":66000,"med_+_iqr":7849736019.758692},{"atEval":69000,"med_+_iqr":6528238838626.165},{"atEval":72000,"med_+_iqr":7749695090.063854},{"atEval":75000,"med_+_iqr":112569783.3200241},{"atEval":78000,"med_+_iqr":987133435486.5302},{"atEval":81000,"med_+_iqr":1908751963.5016487},{"atEval":84000,"med_+_iqr":11477224135572.623},{"atEval":87000,"med_+_iqr":152202.33090219944},{"atEval":90000,"med_+_iqr":12437424985.020008},{"atEval":93000,"med_+_iqr":2701958981.043655},{"atEval":96000,"med_+_iqr":227550364725.3342},{"atEval":99000,"med_+_iqr":16972856038.763058},{"atEval":102000,"med_+_iqr":5778146953.824808},{"atEval":105000,"med_+_iqr":105522763090.6796},{"atEval":108000,"med_+_iqr":19759426.436170183},{"atEval":111000,"med_+_iqr":7082639555.578114},{"atEval":114000,"med_+_iqr":211890950831.92392},{"atEval":117000,"med_+_iqr":16039870.849435473},{"atEval":120000,"med_+_iqr":37215090132.52681},{"atEval":123000,"med_+_iqr":5294237.158827769},{"atEval":126000,"med_+_iqr":10734156.018931136},{"atEval":129000,"med_+_iqr":83524273356.04787},{"atEval":132000,"med_+_iqr":1420326144684.0208},{"atEval":135000,"med_+_iqr":10846215220.372217},{"atEval":138000,"med_+_iqr":7190218666.74241},{"atEval":141000,"med_+_iqr":696424333.396187},{"atEval":144000,"med_+_iqr":2136928014815.1548},{"atEval":147000,"med_+_iqr":66790077797.2298},{"atEval":150000,"med_+_iqr":32908552.60301277},{"atEval":153000,"med_+_iqr":340152.650749555},{"atEval":156000,"med_+_iqr":547070513.83875},{"atEval":159000,"med_+_iqr":668424712.601296},{"atEval":162000,"med_+_iqr":2924752942712.779},{"atEval":165000,"med_+_iqr":21695940031.707664},{"atEval":168000,"med_+_iqr":4751278999.647847},{"atEval":171000,"med_+_iqr":520403115.2106274},{"atEval":174000,"med_+_iqr":27650992523.321217},{"atEval":177000,"med_+_iqr":1347949127024.2917},{"atEval":180000,"med_+_iqr":4497596646.958444},{"atEval":183000,"med_+_iqr":8693.277872124881},{"atEval":186000,"med_+_iqr":4637881879.737768},{"atEval":189000,"med_+_iqr":44968325607.78452},{"atEval":192000,"med_+_iqr":1832.9192052922235},{"atEval":195000,"med_+_iqr":29138783977.22478},{"atEval":198000,"med_+_iqr":45121193.11563886},{"atEval":201000,"med_+_iqr":20748477125.67668},{"atEval":204000,"med_+_iqr":5030264186.450021},{"atEval":207000,"med_+_iqr":668275623002.5792},{"atEval":210000,"med_+_iqr":7194218087.500372},{"atEval":213000,"med_+_iqr":368017002693.3472},{"atEval":216000,"med_+_iqr":456357.648231651},{"atEval":219000,"med_+_iqr":577545143560.1852},{"atEval":222000,"med_+_iqr":541986742.0948265},{"atEval":225000,"med_+_iqr":13626514.494466603},{"atEval":228000,"med_+_iqr":4846381904849.241},{"atEval":231000,"med_+_iqr":1126440171126.936},{"atEval":234000,"med_+_iqr":11875561774194.508},{"atEval":237000,"med_+_iqr":143395931288.7031},{"atEval":240000,"med_+_iqr":167590603066.5473},{"atEval":243000,"med_+_iqr":14638266919.507723},{"atEval":246000,"med_+_iqr":65570076.192965515},{"atEval":249000,"med_+_iqr":2203327110.8281364},{"atEval":252000,"med_+_iqr":15150190540.276184},{"atEval":255000,"med_+_iqr":21504884521.489758},{"atEval":258000,"med_+_iqr":122843555.90390244},{"atEval":261000,"med_+_iqr":32555001298.56871},{"atEval":264000,"med_+_iqr":140408373.47525695},{"atEval":267000,"med_+_iqr":1718285832.6069152},{"atEval":270000,"med_+_iqr":6005.953795142804},{"atEval":273000,"med_+_iqr":4360610302.588879},{"atEval":276000,"med_+_iqr":43569587.33994854},{"atEval":279000,"med_+_iqr":0.43736084267606895},{"atEval":282000,"med_+_iqr":18085323442649.02},{"atEval":285000,"med_+_iqr":3624174161.1674604},{"atEval":288000,"med_+_iqr":50567011038439.42},{"atEval":291000,"med_+_iqr":11125951753.273907},{"atEval":294000,"med_+_iqr":0.00011558894268340377},{"atEval":297000,"med_+_iqr":44740935478.160866},{"atEval":300000,"med_+_iqr":37865742421488.96}]},{"baseLevel-popSize":30,"baseLevel-problemId":"SCHWEFEL223","baseLevel-sampleSize":30,"baseLevel-xDim":50,"baseLevelEvals":100,"bestParameters":{"OptimizerChainInitializerSimplex":{"perturbator":{"lowerBound":0.0,"upperBound":1.0,"value":0.766051933064188},"refiner":{"lowerBound":0.0,"upperBound":1.0,"value":0.23394806693581202}},"OptimizerChainPerturbatorSimplex":{"refiner":{"lowerBound":0.0,"upperBound":1.0,"value":0.5702802949664882},"selector":{"lowerBound":0.0,"upperBound":1.0,"value":0.42971970503351176}},"OptimizerChainRefinerSimplex":{"refiner":{"lowerBound":0.0,"upperBound":1.0,"value":0.3121328564351055},"selector":{"lowerBound":0.0,"upperBound":1.0,"value":0.6878671435648944}},"OptimizerChainSelectorSimplex":{"perturbator":{"lowerBound":0.0,"upperBound":1.0,"value":1.0}},"PerturbatorDEOperatorParams":{"DE_CR":{"lowerBound":0.9,"upperBound":1.0,"value":0.9596898352224258},"DE_FORCE":{"lowerBound":0.4,"upperBound":0.7,"value":0.5200121250024576}},"PerturbatorDESimplex":{"DE":{"lowerBound":0.0,"upperBound":1.0,"value":0.0021409975922130897},"GA":{"lowerBound":0.0,"upperBound":1.0,"value":0.9978590024077869}},"PerturbatorGAOperatorParams":{"GA_ALPHA":{"lowerBound":0.0,"upperBound":1.0,"value":0.46295476412329234},"GA_CR":{"lowerBound":0.0,"upperBound":1.0,"value":0.13441247075761595},"GA_CR_POINT":{"lowerBound":0.0,"upperBound":1.0,"value":0.8821436610198096},"GA_MUTATION_RATE":{"lowerBound":0.0,"upperBound":1.0,"value":0.8422797384509563},"GA_MUTATION_SIZE":{"lowerBound":0.0,"upperBound":1000.0,"value":284.0251107152119},"GA_PARENTPOOL_RATIO":{"lowerBound":0.2,"upperBound":1.0,"value":0.2830421847793589}},"PerturbatorGASimplex":{"DE":{"lowerBound":0.0,"upperBound":1.0,"value":0.27069979137619116},"GA":{"lowerBound":0.0,"upperBound":1.0,"value":0.7293002086238088}},"PerturbatorInitializerSimplex":{"DE":{"lowerBound":0.0,"upperBound":1.0,"value":0.8727660010384787},"GA":{"lowerBound":0.0,"upperBound":1.0,"value":0.12723399896152135}},"RefinerGDOperatorParams":{"GD_ALPHA":{"lowerBound":0.5,"upperBound":5.0,"value":4.464400059846424},"GD_FEVALS":{"lowerBound":1.0,"upperBound":100.0,"value":3.241927547717963}},"RefinerGDSimplex":{"GD":{"lowerBound":0.0,"upperBound":1.0,"value":0.982952872866636},"LBFGS":{"lowerBound":0.0,"upperBound":1.0,"value":0.017047127133364034}},"RefinerInitializerSimplex":{"GD":{"lowerBound":0.0,"upperBound":1.0,"value":0.8256073445759966},"LBFGS":{"lowerBound":0.0,"upperBound":1.0,"value":0.17439265542400345}},"RefinerLBFGSOperatorParams":{"LBFGS_ALPHA":{"lowerBound":0.5,"upperBound":5.0,"value":2.559477165007233},"LBFGS_C1":{"lowerBound":0.0,"upperBound":0.1,"value":0.06876297790586032},"LBFGS_C2":{"lowerBound":0.8,"upperBound":1.0,"value":0.9292255052518298},"LBFGS_FEVALS":{"lowerBound":1.0,"upperBound":100.0,"value":15.484639124804248}},"RefinerLBFGSSimplex":{"GD":{"lowerBound":0.0,"upperBound":1.0,"value":0.6157587382872542},"LBFGS":{"lowerBound":0.0,"upperBound":1.0,"value":0.3842412617127457}},"SelectorBestSimplex":{"best":{"lowerBound":0.0,"upperBound":1.0,"value":1.0}},"SelectorInitializerSimplex":{"best":{"lowerBound":0.0,"upperBound":1.0,"value":1.0}}},"experimentHashSha256":"80f173a731083bf2aa148e4f18d38078f5fb073a67f6af7183322ca3d95a6f17","hyperLevel-id":"random","minBaseLevelStatistic":0.000973397331588083,"trialCount":100,"trials":[{"atEval":3000,"med_+_iqr":1.0007850340582266e+17},{"atEval":6000,"med_+_iqr":5.956881954466055e+16},{"atEval":9000,"med_+_iqr":7.32782877679052e+17},{"atEval":12000,"med_+_iqr":2.5296782733396906e+17},{"atEval":15000,"med_+_iqr":2.133612795556298e+18},{"atEval":18000,"med_+_iqr":0.000973397331588083},{"atEval":21000,"med_+_iqr":3.641575213905659e+17},{"atEval":24000,"med_+_iqr":7.849083906506958e+15},{"atEval":27000,"med_+_iqr":1.0272408481942352e+17},{"atEval":30000,"med_+_iqr":1.8723326423653728e+16},{"atEval":33000,"med_+_iqr":4.6241574958797816e+16},{"atEval":36000,"med_+_iqr":1.162460824179991e+19},{"atEval":39000,"med_+_iqr":706519145341.4594},{"atEval":42000,"med_+_iqr":7.767963709236411e+17},{"atEval":45000,"med_+_iqr":4.2258978625697824e+16},{"atEval":48000,"med_+_iqr":3.931970022552006e+17},{"atEval":51000,"med_+_iqr":1.3021279692771835e+18},{"atEval":54000,"med_+_iqr":1.9160625107871315e+15},{"atEval":57000,"med_+_iqr":1.3153268038721621e+17},{"atEval":60000,"med_+_iqr":1.3873820999026086e+17},{"atEval":63000,"med_+_iqr":8.974582846034853e+16},{"atEval":66000,"med_+_iqr":6.030615617345824e+16},{"atEval":69000,"med_+_iqr":463740695309528.4},{"atEval":72000,"med_+_iqr":2.279488265718064e+16},{"atEval":75000,"med_+_iqr":3.3937179300161295e+15},{"atEval":78000,"med_+_iqr":3.9107401176263547e+18},{"atEval":81000,"med_+_iqr":1.1885346175111133e+17},{"atEval":84000,"med_+_iqr":1.1984769254955128e+17},{"atEval":87000,"med_+_iqr":1156346512.118583},{"atEval":90000,"med_+_iqr":6.384651523603432e+18},{"atEval":93000,"med_+_iqr":6.859158182647532e+18},{"atEval":96000,"med_+_iqr":1.594906973501353e+17},{"atEval":99000,"med_+_iqr":4.6219600849161456e+16},{"atEval":102000,"med_+_iqr":5.439872349713806e+17},{"atEval":105000,"med_+_iqr":9.395026311395217e+17},{"atEval":108000,"med_+_iqr":3.5470557381214445e+17},{"atEval":111000,"med_+_iqr":4.3035962098478104e+16},{"atEval":114000,"med_+_iqr":33586589217909.457},{"atEval":117000,"med_+_iqr":2.4220874297089106e+18},{"atEval":120000,"med_+_iqr":1.9709247091881094e+17},{"atEval":123000,"med_+_iqr":1.342352049424792e+15},{"atEval":126000,"med_+_iqr":374767287136123.0},{"atEval":129000,"med_+_iqr":2.741735599662331e+17},{"atEval":132000,"med_+_iqr":1.2906800358317502e+19},{"atEval":135000,"med_+_iqr":2.865659785335851e+15},{"atEval":138000,"med_+_iqr":1.4232793751451425e+15},{"atEval":141000,"med_+_iqr":3.9430092722499645e+18},{"atEval":144000,"med_+_iqr":1.1611845508846604e+16},{"atEval":147000,"med_+_iqr":44038261369.00928},{"atEval":150000,"med_+_iqr":658435537284812.5},{"atEval":153000,"med_+_iqr":7.667446104063013e+16},{"atEval":156000,"med_+_iqr":5.51144552766477e+17},{"atEval":159000,"med_+_iqr":2.806665016050078e+18},{"atEval":162000,"med_+_iqr":2.922281819646689e+18},{"atEval":165000,"med_+_iqr":9.499926843612571e+19},{"atEval":168000,"med_+_iqr":2.0612484800094188e+18},{"atEval":171000,"med_+_iqr":154801608288238.37},{"atEval":174000,"med_+_iqr":1.027369125628099e+17},{"atEval":177000,"med_+_iqr":8.814457535549133e+16},{"atEval":180000,"med_+_iqr":1.627496080472215e+15},{"atEval":183000,"med_+_iqr":3.713432618372329e+18},{"atEval":186000,"med_+_iqr":2.2190953201526292e+16},{"atEval":189000,"med_+_iqr":3.7904824362449684e+18},{"atEval":192000,"med_+_iqr":4.0244176596697636e+18},{"atEval":195000,"med_+_iqr":1.0611050165821403e+18},{"atEval":198000,"med_+_iqr":4.924902444220295e+18},{"atEval":201000,"med_+_iqr":7.110008773128157e+17},{"atEval":204000,"med_+_iqr":1.4308354083397014e+17},{"atEval":207000,"med_+_iqr":1.3914849692540389e+17},{"atEval":210000,"med_+_iqr":1.8022366615265841e+19},{"atEval":213000,"med_+_iqr":4.605797983277671e+16},{"atEval":216000,"med_+_iqr":2.4089563865129312e+19},{"atEval":219000,"med_+_iqr":14751898319087.219},{"atEval":222000,"med_+_iqr":1.6671618150128005e+18},{"atEval":225000,"med_+_iqr":1.4781716724919315e+17},{"atEval":228000,"med_+_iqr":9.811753975083677e+16},{"atEval":231000,"med_+_iqr":1.1142766420013414e+17},{"atEval":234000,"med_+_iqr":1.035954407557254e+16},{"atEval":237000,"med_+_iqr":1.2462918272532555e+17},{"atEval":240000,"med_+_iqr":3.601708924491227e+15},{"atEval":243000,"med_+_iqr":8.702558512293795e+17},{"atEval":246000,"med_+_iqr":1.3690879005219945e+15},{"atEval":249000,"med_+_iqr":1.106223162443964e+17},{"atEval":252000,"med_+_iqr":7.113263700548063e+16},{"atEval":255000,"med_+_iqr":2.4739764169869848e+16},{"atEval":258000,"med_+_iqr":54142302610798.664},{"atEval":261000,"med_+_iqr":1.1320652867976212e+15},{"atEval":264000,"med_+_iqr":2.5862834579680773e+18},{"atEval":267000,"med_+_iqr":1.9441133222492787e+17},{"atEval":270000,"med_+_iqr":7.469234710912939e+16},{"atEval":273000,"med_+_iqr":1.7859944374606765e+17},{"atEval":276000,"med_+_iqr":837876060040236.6},{"atEval":279000,"med_+_iqr":1.142101886121939e+17},{"atEval":282000,"med_+_iqr":2.9993668026911676e+16},{"atEval":285000,"med_+_iqr":1.2934708446630055e+15},{"atEval":288000,"med_+_iqr":2.7768192938479312e+16},{"atEval":291000,"med_+_iqr":2.3029473971889937e+20},{"atEval":294000,"med_+_iqr":2.592746702637395e+18},{"atEval":297000,"med_+_iqr":6.1241854591753136e+16},{"atEval":300000,"med_+_iqr":1.15799388334739e+15}]},{"baseLevel-popSize":30,"baseLevel-problemId":"SCHWEFEL223","baseLevel-sampleSize":30,"baseLevel-xDim":100,"baseLevelEvals":100,"bestParameters":{"OptimizerChainInitializerSimplex":{"perturbator":{"lowerBound":0.0,"upperBound":1.0,"value":0.46197734293426584},"refiner":{"lowerBound":0.0,"upperBound":1.0,"value":0.5380226570657342}},"OptimizerChainPerturbatorSimplex":{"refiner":{"lowerBound":0.0,"upperBound":1.0,"value":0.735671493863922},"selector":{"lowerBound":0.0,"upperBound":1.0,"value":0.26432850613607795}},"OptimizerChainRefinerSimplex":{"refiner":{"lowerBound":0.0,"upperBound":1.0,"value":0.3171524760687917},"selector":{"lowerBound":0.0,"upperBound":1.0,"value":0.6828475239312083}},"OptimizerChainSelectorSimplex":{"perturbator":{"lowerBound":0.0,"upperBound":1.0,"value":1.0}},"PerturbatorDEOperatorParams":{"DE_CR":{"lowerBound":0.9,"upperBound":1.0,"value":0.9303971786876197},"DE_FORCE":{"lowerBound":0.4,"upperBound":0.7,"value":0.4725735948746923}},"PerturbatorDESimplex":{"DE":{"lowerBound":0.0,"upperBound":1.0,"value":0.8809829373068208},"GA":{"lowerBound":0.0,"upperBound":1.0,"value":0.1190170626931792}},"PerturbatorGAOperatorParams":{"GA_ALPHA":{"lowerBound":0.0,"upperBound":1.0,"value":0.25989063616271363},"GA_CR":{"lowerBound":0.0,"upperBound":1.0,"value":0.3899070551949302},"GA_CR_POINT":{"lowerBound":0.0,"upperBound":1.0,"value":0.08812697102380596},"GA_MUTATION_RATE":{"lowerBound":0.0,"upperBound":1.0,"value":0.868068295092811},"GA_MUTATION_SIZE":{"lowerBound":0.0,"upperBound":1000.0,"value":953.227861938457},"GA_PARENTPOOL_RATIO":{"lowerBound":0.2,"upperBound":1.0,"value":0.4810945789810041}},"PerturbatorGASimplex":{"DE":{"lowerBound":0.0,"upperBound":1.0,"value":0.036314541693042934},"GA":{"lowerBound":0.0,"upperBound":1.0,"value":0.9636854583069571}},"PerturbatorInitializerSimplex":{"DE":{"lowerBound":0.0,"upperBound":1.0,"value":0.8385960912775199},"GA":{"lowerBound":0.0,"upperBound":1.0,"value":0.16140390872248014}},"RefinerGDOperatorParams":{"GD_ALPHA":{"lowerBound":0.5,"upperBound":5.0,"value":2.425609650168665},"GD_FEVALS":{"lowerBound":1.0,"upperBound":100.0,"value":6.60976157258435}},"RefinerGDSimplex":{"GD":{"lowerBound":0.0,"upperBound":1.0,"value":0.48206315180420334},"LBFGS":{"lowerBound":0.0,"upperBound":1.0,"value":0.5179368481957967}},"RefinerInitializerSimplex":{"GD":{"lowerBound":0.0,"upperBound":1.0,"value":0.572425807036302},"LBFGS":{"lowerBound":0.0,"upperBound":1.0,"value":0.427574192963698}},"RefinerLBFGSOperatorParams":{"LBFGS_ALPHA":{"lowerBound":0.5,"upperBound":5.0,"value":4.14617002465258},"LBFGS_C1":{"lowerBound":0.0,"upperBound":0.1,"value":0.004687484559863658},"LBFGS_C2":{"lowerBound":0.8,"upperBound":1.0,"value":0.8528719226314065},"LBFGS_FEVALS":{"lowerBound":1.0,"upperBound":100.0,"value":12.968164126529402}},"RefinerLBFGSSimplex":{"GD":{"lowerBound":0.0,"upperBound":1.0,"value":0.8118578667458143},"LBFGS":{"lowerBound":0.0,"upperBound":1.0,"value":0.18814213325418566}},"SelectorBestSimplex":{"best":{"lowerBound":0.0,"upperBound":1.0,"value":1.0}},"SelectorInitializerSimplex":{"best":{"lowerBound":0.0,"upperBound":1.0,"value":1.0}}},"experimentHashSha256":"b3d0f3dcf7b0587d8231d9c0960a46f3d19c3f211bee41b0f3b9ee20ac7fc8e1","hyperLevel-id":"random","minBaseLevelStatistic":1756348958578.3005,"trialCount":100,"trials":[{"atEval":3000,"med_+_iqr":3.6384050374316717e+17},{"atEval":6000,"med_+_iqr":5.137942272014201e+20},{"atEval":9000,"med_+_iqr":1.1366325874872807e+19},{"atEval":12000,"med_+_iqr":1.4903060737376886e+17},{"atEval":15000,"med_+_iqr":2.7501618737209293e+17},{"atEval":18000,"med_+_iqr":1.3969196566260706e+17},{"atEval":21000,"med_+_iqr":6.202616930997966e+18},{"atEval":24000,"med_+_iqr":1.8261453560469789e+19},{"atEval":27000,"med_+_iqr":5.273601477263991e+16},{"atEval":30000,"med_+_iqr":1.5341906669806027e+19},{"atEval":33000,"med_+_iqr":8.327935964188447e+18},{"atEval":36000,"med_+_iqr":6.341318177960532e+17},{"atEval":39000,"med_+_iqr":6.511538047279411e+20},{"atEval":42000,"med_+_iqr":6.588588249250895e+17},{"atEval":45000,"med_+_iqr":2.369315696367595e+19},{"atEval":48000,"med_+_iqr":5.676010172612212e+18},{"atEval":51000,"med_+_iqr":1.1789313161158991e+18},{"atEval":54000,"med_+_iqr":8.725661190314706e+18},{"atEval":57000,"med_+_iqr":3.3708813500574605e+17},{"atEval":60000,"med_+_iqr":1.651861621453658e+17},{"atEval":63000,"med_+_iqr":9.39732553797892e+15},{"atEval":66000,"med_+_iqr":3.747665680378802e+20},{"atEval":69000,"med_+_iqr":1.773458153355746e+19},{"atEval":72000,"med_+_iqr":2.559035069805059e+15},{"atEval":75000,"med_+_iqr":3.903630062852725e+17},{"atEval":78000,"med_+_iqr":1.5774745017306635e+15},{"atEval":81000,"med_+_iqr":1.6712775737053088e+17},{"atEval":84000,"med_+_iqr":3.2334513867607424e+18},{"atEval":87000,"med_+_iqr":1.8288217460431548e+15},{"atEval":90000,"med_+_iqr":3.493740352039014e+15},{"atEval":93000,"med_+_iqr":4.260073249814691e+17},{"atEval":96000,"med_+_iqr":4.1624121413453965e+20},{"atEval":99000,"med_+_iqr":1.5288815777432358e+15},{"atEval":102000,"med_+_iqr":5.5209008198606323e+17},{"atEval":105000,"med_+_iqr":3404927718721.505},{"atEval":108000,"med_+_iqr":6.837459115955517e+17},{"atEval":111000,"med_+_iqr":34204383091687.793},{"atEval":114000,"med_+_iqr":5.306512294495519e+18},{"atEval":117000,"med_+_iqr":2.6090203416443974e+17},{"atEval":120000,"med_+_iqr":2.947419580859954e+17},{"atEval":123000,"med_+_iqr":2.507464106068315e+17},{"atEval":126000,"med_+_iqr":6.929274962362943e+18},{"atEval":129000,"med_+_iqr":4.641638823851873e+19},{"atEval":132000,"med_+_iqr":7.612908113510545e+18},{"atEval":135000,"med_+_iqr":2.1316333776503904e+17},{"atEval":138000,"med_+_iqr":2.8933918534543294e+19},{"atEval":141000,"med_+_iqr":2.4048802703789457e+19},{"atEval":144000,"med_+_iqr":4.005477605429618e+20},{"atEval":147000,"med_+_iqr":1.3932396071280271e+19},{"atEval":150000,"med_+_iqr":2.2101187481434784e+17},{"atEval":153000,"med_+_iqr":6.574479510280067e+15},{"atEval":156000,"med_+_iqr":1.6174137156169236e+19},{"atEval":159000,"med_+_iqr":4.056048309679951e+17},{"atEval":162000,"med_+_iqr":1.9284698612555893e+15},{"atEval":165000,"med_+_iqr":2.051066993492997e+19},{"atEval":168000,"med_+_iqr":2.6491700089456394e+19},{"atEval":171000,"med_+_iqr":3.40541157371633e+19},{"atEval":174000,"med_+_iqr":3.83955681363543e+19},{"atEval":177000,"med_+_iqr":2.882826590104281e+15},{"atEval":180000,"med_+_iqr":2.9703912499311475e+17},{"atEval":183000,"med_+_iqr":4.13858741006193e+17},{"atEval":186000,"med_+_iqr":5.902899902391735e+19},{"atEval":189000,"med_+_iqr":1.908635388666763e+19},{"atEval":192000,"med_+_iqr":445207712774642.75},{"atEval":195000,"med_+_iqr":3.59103802174622e+15},{"atEval":198000,"med_+_iqr":9.649350335390421e+16},{"atEval":201000,"med_+_iqr":2.5044169340114076e+19},{"atEval":204000,"med_+_iqr":3.168751762539548e+15},{"atEval":207000,"med_+_iqr":1.6700238678849616e+19},{"atEval":210000,"med_+_iqr":2.8679189563377213e+19},{"atEval":213000,"med_+_iqr":5.253793267605083e+17},{"atEval":216000,"med_+_iqr":1756348958578.3005},{"atEval":219000,"med_+_iqr":1.9421722705841308e+18},{"atEval":222000,"med_+_iqr":6.731177036299201e+18},{"atEval":225000,"med_+_iqr":2.1159482564977307e+15},{"atEval":228000,"med_+_iqr":4.697697564017707e+19},{"atEval":231000,"med_+_iqr":2.038713870941646e+19},{"atEval":234000,"med_+_iqr":1.1433642206085072e+17},{"atEval":237000,"med_+_iqr":8.638344682043732e+15},{"atEval":240000,"med_+_iqr":2.8820401434518627e+17},{"atEval":243000,"med_+_iqr":3.95703556360319e+20},{"atEval":246000,"med_+_iqr":3.736761522577027e+18},{"atEval":249000,"med_+_iqr":3.2095837303065276e+19},{"atEval":252000,"med_+_iqr":6.821883249211577e+18},{"atEval":255000,"med_+_iqr":67520841232742.875},{"atEval":258000,"med_+_iqr":1.2328299310308102e+17},{"atEval":261000,"med_+_iqr":4.316330724690863e+16},{"atEval":264000,"med_+_iqr":3.0746880199843717e+19},{"atEval":267000,"med_+_iqr":1.9230892231888376e+18},{"atEval":270000,"med_+_iqr":1.4063084688432734e+19},{"atEval":273000,"med_+_iqr":2.5896351290646362e+17},{"atEval":276000,"med_+_iqr":7.874366741713079e+18},{"atEval":279000,"med_+_iqr":1.6508848830997467e+19},{"atEval":282000,"med_+_iqr":6.586235241133927e+20},{"atEval":285000,"med_+_iqr":7.016545754939114e+17},{"atEval":288000,"med_+_iqr":3.1867936044380512e+19},{"atEval":291000,"med_+_iqr":2.6968731828906458e+17},{"atEval":294000,"med_+_iqr":1.7355037733385138e+19},{"atEval":297000,"med_+_iqr":4.34247990483779e+15},{"atEval":300000,"med_+_iqr":2.830756870872503e+17}]},{"baseLevel-popSize":30,"baseLevel-problemId":"SCHWEFEL223","baseLevel-sampleSize":30,"baseLevel-xDim":500,"baseLevelEvals":100,"bestParameters":{"OptimizerChainInitializerSimplex":{"perturbator":{"lowerBound":0.0,"upperBound":1.0,"value":0.7313459405167808},"refiner":{"lowerBound":0.0,"upperBound":1.0,"value":0.26865405948321913}},"OptimizerChainPerturbatorSimplex":{"refiner":{"lowerBound":0.0,"upperBound":1.0,"value":0.6257566526307238},"selector":{"lowerBound":0.0,"upperBound":1.0,"value":0.3742433473692762}},"OptimizerChainRefinerSimplex":{"refiner":{"lowerBound":0.0,"upperBound":1.0,"value":0.3670841206782387},"selector":{"lowerBound":0.0,"upperBound":1.0,"value":0.6329158793217613}},"OptimizerChainSelectorSimplex":{"perturbator":{"lowerBound":0.0,"upperBound":1.0,"value":1.0}},"PerturbatorDEOperatorParams":{"DE_CR":{"lowerBound":0.9,"upperBound":1.0,"value":0.99517324509399},"DE_FORCE":{"lowerBound":0.4,"upperBound":0.7,"value":0.4268774470746096}},"PerturbatorDESimplex":{"DE":{"lowerBound":0.0,"upperBound":1.0,"value":0.2643180856119728},"GA":{"lowerBound":0.0,"upperBound":1.0,"value":0.7356819143880272}},"PerturbatorGAOperatorParams":{"GA_ALPHA":{"lowerBound":0.0,"upperBound":1.0,"value":0.46454655809481865},"GA_CR":{"lowerBound":0.0,"upperBound":1.0,"value":0.21121758839631963},"GA_CR_POINT":{"lowerBound":0.0,"upperBound":1.0,"value":0.4403503967575315},"GA_MUTATION_RATE":{"lowerBound":0.0,"upperBound":1.0,"value":0.8631351862732308},"GA_MUTATION_SIZE":{"lowerBound":0.0,"upperBound":1000.0,"value":12.270595759350526},"GA_PARENTPOOL_RATIO":{"lowerBound":0.2,"upperBound":1.0,"value":0.7366867673526765}},"PerturbatorGASimplex":{"DE":{"lowerBound":0.0,"upperBound":1.0,"value":0.690278516884304},"GA":{"lowerBound":0.0,"upperBound":1.0,"value":0.309721483115696}},"PerturbatorInitializerSimplex":{"DE":{"lowerBound":0.0,"upperBound":1.0,"value":0.4628419390029669},"GA":{"lowerBound":0.0,"upperBound":1.0,"value":0.5371580609970331}},"RefinerGDOperatorParams":{"GD_ALPHA":{"lowerBound":0.5,"upperBound":5.0,"value":4.834733014748183},"GD_FEVALS":{"lowerBound":1.0,"upperBound":100.0,"value":1.5672100998192324}},"RefinerGDSimplex":{"GD":{"lowerBound":0.0,"upperBound":1.0,"value":0.9267599618562987},"LBFGS":{"lowerBound":0.0,"upperBound":1.0,"value":0.07324003814370131}},"RefinerInitializerSimplex":{"GD":{"lowerBound":0.0,"upperBound":1.0,"value":0.8138420984558506},"LBFGS":{"lowerBound":0.0,"upperBound":1.0,"value":0.18615790154414935}},"RefinerLBFGSOperatorParams":{"LBFGS_ALPHA":{"lowerBound":0.5,"upperBound":5.0,"value":4.450964573973373},"LBFGS_C1":{"lowerBound":0.0,"upperBound":0.1,"value":0.06967509652243652},"LBFGS_C2":{"lowerBound":0.8,"upperBound":1.0,"value":0.9571741818493603},"LBFGS_FEVALS":{"lowerBound":1.0,"upperBound":100.0,"value":62.482454620067536}},"RefinerLBFGSSimplex":{"GD":{"lowerBound":0.0,"upperBound":1.0,"value":0.7826644814008467},"LBFGS":{"lowerBound":0.0,"upperBound":1.0,"value":0.21733551859915332}},"SelectorBestSimplex":{"best":{"lowerBound":0.0,"upperBound":1.0,"value":1.0}},"SelectorInitializerSimplex":{"best":{"lowerBound":0.0,"upperBound":1.0,"value":1.0}}},"experimentHashSha256":"adb5fccd26442124a2a3e0f4d3d7b54983999fa261f2c4215fcc261a9c3a2856","hyperLevel-id":"random","minBaseLevelStatistic":6627183.934802984,"trialCount":100,"trials":[{"atEval":3000,"med_+_iqr":4.547407686406988e+20},{"atEval":6000,"med_+_iqr":2.997021388498716e+19},{"atEval":9000,"med_+_iqr":1.1650197980238917e+18},{"atEval":12000,"med_+_iqr":3.4277432897463198e+19},{"atEval":15000,"med_+_iqr":1.206603593409033e+20},{"atEval":18000,"med_+_iqr":5.304295423192635e+19},{"atEval":21000,"med_+_iqr":3.3158462563246674e+18},{"atEval":24000,"med_+_iqr":1.2883311464113142e+16},{"atEval":27000,"med_+_iqr":6627183.934802984},{"atEval":30000,"med_+_iqr":1.840070889567502e+20},{"atEval":33000,"med_+_iqr":6.546374518560752e+18},{"atEval":36000,"med_+_iqr":332273119820833.8},{"atEval":39000,"med_+_iqr":9.037666070266765e+19},{"atEval":42000,"med_+_iqr":1.3381614764953564e+18},{"atEval":45000,"med_+_iqr":1.9950159343529974e+20},{"atEval":48000,"med_+_iqr":2.5457833230436103e+20},{"atEval":51000,"med_+_iqr":2.7570609064881276e+16},{"atEval":54000,"med_+_iqr":5.589620142423179e+17},{"atEval":57000,"med_+_iqr":1.1593182266572383e+18},{"atEval":60000,"med_+_iqr":6.438265437479239e+18},{"atEval":63000,"med_+_iqr":8.363984321749562e+20},{"atEval":66000,"med_+_iqr":4.106148681542596e+21},{"atEval":69000,"med_+_iqr":1.7085263323676646e+16},{"atEval":72000,"med_+_iqr":1.0593838153811726e+21},{"atEval":75000,"med_+_iqr":8.899927862350319e+19},{"atEval":78000,"med_+_iqr":1.8144440297338365e+18},{"atEval":81000,"med_+_iqr":3.009733190940214e+18},{"atEval":84000,"med_+_iqr":6.365244381272588e+18},{"atEval":87000,"med_+_iqr":2.510303674279638e+20},{"atEval":90000,"med_+_iqr":1.0564116907374412e+19},{"atEval":93000,"med_+_iqr":8.921626082086217e+19},{"atEval":96000,"med_+_iqr":7.012212499324267e+21},{"atEval":99000,"med_+_iqr":2.2089091631439158e+20},{"atEval":102000,"med_+_iqr":1.7305488651253199e+19},{"atEval":105000,"med_+_iqr":4.4310067053520456e+18},{"atEval":108000,"med_+_iqr":9.707596492359162e+19},{"atEval":111000,"med_+_iqr":1.0782647791864768e+20},{"atEval":114000,"med_+_iqr":3.7669481848307e+21},{"atEval":117000,"med_+_iqr":1.0221307410312313e+20},{"atEval":120000,"med_+_iqr":6.073447615958459e+16},{"atEval":123000,"med_+_iqr":1.2199792994524854e+18},{"atEval":126000,"med_+_iqr":2.333142707369894e+18},{"atEval":129000,"med_+_iqr":9.373452707166054e+19},{"atEval":132000,"med_+_iqr":2.394119810885435e+17},{"atEval":135000,"med_+_iqr":8.663801483965723e+19},{"atEval":138000,"med_+_iqr":984577736585739.3},{"atEval":141000,"med_+_iqr":2.0345282635640504e+16},{"atEval":144000,"med_+_iqr":1.0577763962867666e+20},{"atEval":147000,"med_+_iqr":9.530740072593842e+18},{"atEval":150000,"med_+_iqr":1.47483829232594e+18},{"atEval":153000,"med_+_iqr":9.633584690715487e+19},{"atEval":156000,"med_+_iqr":9.709347028032087e+17},{"atEval":159000,"med_+_iqr":2.7042351270182433e+19},{"atEval":162000,"med_+_iqr":1.0347338995394049e+18},{"atEval":165000,"med_+_iqr":1.1711218365808597e+15},{"atEval":168000,"med_+_iqr":9.614385880083725e+17},{"atEval":171000,"med_+_iqr":1.0403536682038578e+20},{"atEval":174000,"med_+_iqr":3.35714892671416e+20},{"atEval":177000,"med_+_iqr":8.057793333472908e+20},{"atEval":180000,"med_+_iqr":5.966111662685258e+20},{"atEval":183000,"med_+_iqr":7.615675855109697e+20},{"atEval":186000,"med_+_iqr":3.7113468073007367e+21},{"atEval":189000,"med_+_iqr":2.8726201696990465e+20},{"atEval":192000,"med_+_iqr":4.361432821356312e+19},{"atEval":195000,"med_+_iqr":2.0320961579138136e+16},{"atEval":198000,"med_+_iqr":1.5728494239686176e+17},{"atEval":201000,"med_+_iqr":3.8935325549047204e+18},{"atEval":204000,"med_+_iqr":3.614194351894419e+16},{"atEval":207000,"med_+_iqr":9.908040628471901e+19},{"atEval":210000,"med_+_iqr":1.2789906417719386e+20},{"atEval":213000,"med_+_iqr":525872891328722.4},{"atEval":216000,"med_+_iqr":1.5485275793595334e+16},{"atEval":219000,"med_+_iqr":5.7521414316823184e+16},{"atEval":222000,"med_+_iqr":1.6013575758244644e+18},{"atEval":225000,"med_+_iqr":1.6777417328579277e+18},{"atEval":228000,"med_+_iqr":4.0821739787872445e+18},{"atEval":231000,"med_+_iqr":40197325779.462906},{"atEval":234000,"med_+_iqr":1.9494313936390698e+20},{"atEval":237000,"med_+_iqr":1.2279549574370409e+20},{"atEval":240000,"med_+_iqr":3.678403774904504e+21},{"atEval":243000,"med_+_iqr":1.629256588409581e+18},{"atEval":246000,"med_+_iqr":1.4495899191425948e+18},{"atEval":249000,"med_+_iqr":4.2711423462224816e+20},{"atEval":252000,"med_+_iqr":6.930716515159127e+19},{"atEval":255000,"med_+_iqr":2.158499754434127e+18},{"atEval":258000,"med_+_iqr":1.2155817608827378e+20},{"atEval":261000,"med_+_iqr":2.0144744134755672e+19},{"atEval":264000,"med_+_iqr":1.2279934457082462e+20},{"atEval":267000,"med_+_iqr":9.246134889032604e+19},{"atEval":270000,"med_+_iqr":1.457660582267803e+16},{"atEval":273000,"med_+_iqr":4.223317900569803e+18},{"atEval":276000,"med_+_iqr":8.738741389263546e+18},{"atEval":279000,"med_+_iqr":8.092962255811048e+18},{"atEval":282000,"med_+_iqr":1.6434545585857142e+18},{"atEval":285000,"med_+_iqr":6.5529722468243744e+16},{"atEval":288000,"med_+_iqr":8.970547226098152e+19},{"atEval":291000,"med_+_iqr":1.0707661996626573e+18},{"atEval":294000,"med_+_iqr":1.4220809172767514e+18},{"atEval":297000,"med_+_iqr":1.0774926183699998e+21},{"atEval":300000,"med_+_iqr":1.5243900702223053e+18}]}]}