{
    "experiments": {
        "fe499ce1b47d08408a82ca01e7f40e6ad8267d474076fb224acff664a1686dd6": {
            "experiment": {
                "problems": [
                    "PROBLEM_ROSENBROCK",
                    "hhanalysis/logs/SA-MADS-NMHH/GA_DE_GD_LBFGS/bigDim/100/bigPop/100/rosenbrock.json"
                ],
                "baselevelIterations": 100,
                "populationSize": 100,
                "modelSize": 100,
                "trialSampleSizes": 30,
                "trialStepCount": 100,
                "HH-SA-temp": 10000,
                "HH-SA-alpha": 50,
                "hyperLevelMethod": "SA-MADS"
            },
            "metadata": {
                "elapsedTimeSec": 918.5651847840054,
                "threads": 128
            }
        },
        "bd4b5481158005930921b296b3085d507aeb9e8393d708e729425b54f3d3319d": {
            "experiment": {
                "problems": [
                    "PROBLEM_RASTRIGIN",
                    "hhanalysis/logs/SA-MADS-NMHH/GA_DE_GD_LBFGS/bigDim/100/bigPop/100/rastrigin.json"
                ],
                "baselevelIterations": 100,
                "populationSize": 100,
                "modelSize": 100,
                "trialSampleSizes": 30,
                "trialStepCount": 100,
                "HH-SA-temp": 10000,
                "HH-SA-alpha": 50,
                "hyperLevelMethod": "SA-MADS"
            },
            "metadata": {
                "elapsedTimeSec": 354.5333014380303,
                "threads": 128
            }
        },
        "0b1843d287bcf07f2848845511f697f1dc84d2a38a3d3d78f1358d7ef627d147": {
            "experiment": {
                "problems": [
                    "PROBLEM_STYBLINSKITANG",
                    "hhanalysis/logs/SA-MADS-NMHH/GA_DE_GD_LBFGS/bigDim/100/bigPop/100/styblinskitang.json"
                ],
                "baselevelIterations": 100,
                "populationSize": 100,
                "modelSize": 100,
                "trialSampleSizes": 30,
                "trialStepCount": 100,
                "HH-SA-temp": 10000,
                "HH-SA-alpha": 50,
                "hyperLevelMethod": "SA-MADS"
            },
            "metadata": {
                "elapsedTimeSec": 772.9546568910009,
                "threads": 128
            }
        },
        "ca65c69ec274b82c88894e56a3388409b10b102e294a5aacc33ab9a33ed54743": {
            "experiment": {
                "problems": [
                    "PROBLEM_TRID",
                    "hhanalysis/logs/SA-MADS-NMHH/GA_DE_GD_LBFGS/bigDim/100/bigPop/100/trid.json"
                ],
                "baselevelIterations": 100,
                "populationSize": 100,
                "modelSize": 100,
                "trialSampleSizes": 30,
                "trialStepCount": 100,
                "HH-SA-temp": 10000,
                "HH-SA-alpha": 50,
                "hyperLevelMethod": "SA-MADS"
            },
            "metadata": {
                "elapsedTimeSec": 291.22975482500624,
                "threads": 128
            }
        },
        "200f779cdc569d6aab0e550839817d21fc20432911b39a678eb48f0db5f83520": {
            "experiment": {
                "problems": [
                    "PROBLEM_SCHWEFEL223",
                    "hhanalysis/logs/SA-MADS-NMHH/GA_DE_GD_LBFGS/bigDim/100/bigPop/100/schwefel223.json"
                ],
                "baselevelIterations": 100,
                "populationSize": 100,
                "modelSize": 100,
                "trialSampleSizes": 30,
                "trialStepCount": 100,
                "HH-SA-temp": 10000,
                "HH-SA-alpha": 50,
                "hyperLevelMethod": "SA-MADS"
            },
            "metadata": {
                "elapsedTimeSec": 734.1761434570071,
                "threads": 128
            }
        },
        "86a618ba384134403547862a23df3abd15efe1d06489961bd6bb2992f389fc67": {
            "experiment": {
                "problems": [
                    "PROBLEM_QING",
                    "hhanalysis/logs/SA-MADS-NMHH/GA_DE_GD_LBFGS/bigDim/100/bigPop/100/qing.json"
                ],
                "baselevelIterations": 100,
                "populationSize": 100,
                "modelSize": 100,
                "trialSampleSizes": 30,
                "trialStepCount": 100,
                "HH-SA-temp": 10000,
                "HH-SA-alpha": 50,
                "hyperLevelMethod": "SA-MADS"
            },
            "metadata": {
                "elapsedTimeSec": 462.8178184220451,
                "threads": 128
            }
        },
        "e5a97e1f4bdb06b2f2cdac8c6cd14fac31bd369c85fc6fa86a4429c50d5f25be": {
            "experiment": {
                "problems": [
                    "PROBLEM_MICHALEWICZ",
                    "hhanalysis/logs/SA-MADS-NMHH/GA_DE_GD_LBFGS/bigDim/100/bigPop/100/michalewicz.json"
                ],
                "baselevelIterations": 100,
                "populationSize": 100,
                "modelSize": 100,
                "trialSampleSizes": 30,
                "trialStepCount": 100,
                "HH-SA-temp": 10000,
                "HH-SA-alpha": 50,
                "hyperLevelMethod": "SA-MADS"
            },
            "metadata": {
                "elapsedTimeSec": 925.8033811280038,
                "threads": 128
            }
        },
        "6c7d238c4ebc46a515d992f6536d3b76865772c87c829bda10b0e51ee8b3c568": {
            "experiment": {
                "problems": [
                    "PROBLEM_DIXONPRICE",
                    "hhanalysis/logs/SA-MADS-NMHH/GA_DE_GD_LBFGS/bigDim/100/bigPop/100/dixonprice.json"
                ],
                "baselevelIterations": 100,
                "populationSize": 100,
                "modelSize": 100,
                "trialSampleSizes": 30,
                "trialStepCount": 100,
                "HH-SA-temp": 10000,
                "HH-SA-alpha": 50,
                "hyperLevelMethod": "SA-MADS"
            },
            "metadata": {
                "elapsedTimeSec": 1201.3461014060304,
                "threads": 128
            }
        },
        "b1ebddfe418870dd707e3fcfac4a079799f9bed564e6af51f175be2a266f11ab": {
            "experiment": {
                "problems": [
                    "PROBLEM_LEVY",
                    "hhanalysis/logs/SA-MADS-NMHH/GA_DE_GD_LBFGS/bigDim/100/bigPop/100/levy.json"
                ],
                "baselevelIterations": 100,
                "populationSize": 100,
                "modelSize": 100,
                "trialSampleSizes": 30,
                "trialStepCount": 100,
                "HH-SA-temp": 10000,
                "HH-SA-alpha": 50,
                "hyperLevelMethod": "SA-MADS"
            },
            "metadata": {
                "elapsedTimeSec": 784.1219497650163,
                "threads": 128
            }
        },
        "8124ef52d23dbb4ecee0e79a5746d77e5d600f9f21e49d867beeb0c565f877ef": {
            "experiment": {
                "problems": [
                    "PROBLEM_SCHWEFEL",
                    "hhanalysis/logs/SA-MADS-NMHH/GA_DE_GD_LBFGS/bigDim/100/bigPop/100/schwefel.json"
                ],
                "baselevelIterations": 100,
                "populationSize": 100,
                "modelSize": 100,
                "trialSampleSizes": 30,
                "trialStepCount": 100,
                "HH-SA-temp": 10000,
                "HH-SA-alpha": 50,
                "hyperLevelMethod": "SA-MADS"
            },
            "metadata": {
                "elapsedTimeSec": 265.3525275310385,
                "threads": 128
            }
        },
        "625e4d6446dcc43341c9c19779b10ca4ee4614d167f5beb9d2ddb7b0d68f3f51": {
            "experiment": {
                "problems": [
                    "PROBLEM_SUMSQUARES",
                    "hhanalysis/logs/SA-MADS-NMHH/GA_DE_GD_LBFGS/bigDim/100/bigPop/100/sumsquares.json"
                ],
                "baselevelIterations": 100,
                "populationSize": 100,
                "modelSize": 100,
                "trialSampleSizes": 30,
                "trialStepCount": 100,
                "HH-SA-temp": 10000,
                "HH-SA-alpha": 50,
                "hyperLevelMethod": "SA-MADS"
            },
            "metadata": {
                "elapsedTimeSec": 297.60566950397333,
                "threads": 128
            }
        },
        "5cc70d9f6dcd4477b609ea5cf6e512663ff9b96ad3d4a96869fb1416e0c424c4": {
            "experiment": {
                "problems": [
                    "PROBLEM_SPHERE",
                    "hhanalysis/logs/SA-MADS-NMHH/GA_DE_GD_LBFGS/bigDim/100/bigPop/100/sphere.json"
                ],
                "baselevelIterations": 100,
                "populationSize": 100,
                "modelSize": 100,
                "trialSampleSizes": 30,
                "trialStepCount": 100,
                "HH-SA-temp": 10000,
                "HH-SA-alpha": 50,
                "hyperLevelMethod": "SA-MADS"
            },
            "metadata": {
                "elapsedTimeSec": 179.72159205499338,
                "threads": 128
            }
        }
    }
}